gn_py_tracker/__init__.py
gn_py_tracker/event.py
gn_py_tracker/tracker.py
ninja_snake_lib/__init__.py
ninja_snake_lib/decorators.py
ninja_snake_lib/json_formatter.py
ninja_snake_lib/read_dotenv.py
gn_utils_lib-0.1.3.dist-info/LICENSE
gn_utils_lib-0.1.3.dist-info/METADATA
gn_utils_lib-0.1.3.dist-info/WHEEL
gn_utils_lib-0.1.3.dist-info/RECORD
