Metadata-Version: 2.1
Name: gn-utils-lib
Version: 0.1.3
Summary: Biblioteca utilitaria para projetos Python no Getninjas
License: BSD
Author: Goncalo Franco
Author-email: goncalo.franco@getninjas.com.br
Requires-Python: >=3.10,<4.0
Classifier: License :: OSI Approved :: BSD License
Classifier: License :: Other/Proprietary License
Classifier: Programming Language :: Python
Classifier: Programming Language :: Python :: 3
Classifier: Programming Language :: Python :: 3.10
Classifier: Programming Language :: Python :: 3.11
Requires-Dist: django (>=4.2.4,<5.0.0)
Requires-Dist: requests (>=2.31.0,<3.0.0)
Project-URL: Bug Tracker, https://github.com/getninjas/gn-utils-lib/issues
Project-URL: Código, https://github.com/getninjas/gn-utils-lib
